server/__init__.py
server/server.py
server/common/__init__.py
server/common/decos.py
server/common/descryptors.py
server/common/errors.py
server/common/metaclasses.py
server/common/utils.py
server/common/variables.py
server/doc/__init__.py
server/doc/source/__init__.py
server/doc/source/conf.py
server/logs/__init__.py
server/logs/client_log_config.py
server/logs/server_log_config.py
server/server/__init__.py
server/server/add_user.py
server/server/config_window.py
server/server/core.py
server/server/database.py
server/server/main_window.py
server/server/remove_user.py
server/server/stat_window.py
server/unit_tests/__init__.py
server_chat_pyqt_march_24-0.0.1.dist-info/METADATA
server_chat_pyqt_march_24-0.0.1.dist-info/WHEEL
server_chat_pyqt_march_24-0.0.1.dist-info/top_level.txt
server_chat_pyqt_march_24-0.0.1.dist-info/RECORD
